LICENSE.md
README.md
setup.cfg
setup.py
supercollider/__init__.py
supercollider/allocators.py
supercollider/buffer.py
supercollider/bus.py
supercollider/exceptions.py
supercollider/globals.py
supercollider/group.py
supercollider/server.py
supercollider/synth.py
supercollider.egg-info/PKG-INFO
supercollider.egg-info/SOURCES.txt
supercollider.egg-info/dependency_links.txt
supercollider.egg-info/requires.txt
supercollider.egg-info/top_level.txt
tests/test_buffer.py
tests/test_bus.py
tests/test_group.py
tests/test_server.py
tests/test_synth.py