Metadata-Version: 2.1
Name: supercollider
Version: 0.0.6
Summary: Interact with the SuperCollider audio synthesis engine
Home-page: https://github.com/ideoforms/supercollider
Author: Daniel Jones
Author-email: dan-code@erase.net
Keywords: sound,music,supercollider,synthesis
Classifier: Topic :: Multimedia :: Sound/Audio
Classifier: Topic :: Multimedia :: Sound/Audio :: Sound Synthesis
Classifier: Topic :: Artistic Software
Classifier: Topic :: Communications
Classifier: Development Status :: 4 - Beta
Classifier: Intended Audience :: Developers
Requires-Python: >=3.9
License-File: LICENSE.md
Requires-Dist: python-osc
